minion_agent/__init__.py
minion_agent/agent.py
minion_agent/logging.py
minion_agent/config/__init__.py
minion_agent/config/settings.py
minion_agent/frameworks/browser_use.py
minion_agent/frameworks/deep_research.py
minion_agent/frameworks/deep_research_llms.py
minion_agent/frameworks/deep_research_prompts.yaml
minion_agent/frameworks/deep_research_types.py
minion_agent/frameworks/google.py
minion_agent/frameworks/langchain.py
minion_agent/frameworks/minion.py
minion_agent/frameworks/minion_agent.py
minion_agent/frameworks/openai.py
minion_agent/frameworks/smolagents.py
minion_agent/frameworks/tinyagent.py
minion_agent/instructions/__init__.py
minion_agent/instructions/imports.py
minion_agent/providers/__init__.py
minion_agent/providers/adapters.py
minion_agent/serving/__init__.py
minion_agent/serving/agent_card.py
minion_agent/serving/agent_executor.py
minion_agent/serving/server.py
minion_agent/tools/__init__.py
minion_agent/tools/adapters.py
minion_agent/tools/base.py
minion_agent/tools/browser_tool.py
minion_agent/tools/decorators.py
minion_agent/tools/generation.py
minion_agent/tools/image_generation.py
minion_agent/tools/mcp.py
minion_agent/tools/user_interaction.py
minion_agent/tools/web_browsing.py
minion_agent/tools/wrappers.py
minion_agent/tools/mcp/frameworks/__init__.py
minion_agent/tools/mcp/frameworks/agno.py
minion_agent/tools/mcp/frameworks/google.py
minion_agent/tools/mcp/frameworks/langchain.py
minion_agent/tools/mcp/frameworks/llama_index.py
minion_agent/tools/mcp/frameworks/openai.py
minion_agent/tools/mcp/frameworks/smolagents.py
minion_agent/tools/mcp/frameworks/tinyagent.py
minion_agent/utils/__init__.py
minion_agent/utils/logging.py
minion_agent_x-0.1.4.dist-info/METADATA
minion_agent_x-0.1.4.dist-info/WHEEL
minion_agent_x-0.1.4.dist-info/licenses/LICENSE
minion_agent_x-0.1.4.dist-info/RECORD
